MANIFEST.in
README.md
requirements.txt
setup.py
bodylabs_api/__init__.py
bodylabs_api/client.py
bodylabs_api/exceptions.py
bodylabs_api/models.py
bodylabs_api/tests.py
bodylabs_api.egg-info/PKG-INFO
bodylabs_api.egg-info/SOURCES.txt
bodylabs_api.egg-info/dependency_links.txt
bodylabs_api.egg-info/requires.txt
bodylabs_api.egg-info/top_level.txt