Metadata-Version: 1.1
Name: bodylabs-api
Version: 4.1.1
Summary: API client for Bodylabs
Home-page: https://github.com/bodylabs/bodylabs-api-client-py
Author: Body Labs
Author-email: alex@bodylabs.com
License: MIT
Platform: UNKNOWN
Classifier: Development Status :: 3 - Alpha
Classifier: Intended Audience :: Developers
Classifier: License :: OSI Approved :: BSD License
Classifier: Operating System :: OS Independent
Classifier: Programming Language :: Python
